{
  "total_clips": 483,
  "unique_brands": 41,
  "top_brands": [
    {
      "brand": "JOOLA",
      "count": 769
    },
    {
      "brand": "Nike",
      "count": 96
    },
    {
      "brand": "HEAD",
      "count": 32
    },
    {
      "brand": "PICKLEBALL KINGDOM",
      "count": 14
    },
    {
      "brand": "On",
      "count": 11
    },
    {
      "brand": "Joola",
      "count": 7
    },
    {
      "brand": "PBS",
      "count": 5
    },
    {
      "brand": "adidas",
      "count": 4
    },
    {
      "brand": "PKLR",
      "count": 3
    },
    {
      "brand": "H2",
      "count": 3
    },
    {
      "brand": "NIKE",
      "count": 3
    },
    {
      "brand": "PICKLEBALL",
      "count": 3
    },
    {
      "brand": "Courtana",
      "count": 3
    },
    {
      "brand": "Selkirk",
      "count": 3
    },
    {
      "brand": "The Underground",
      "count": 3
    },
    {
      "brand": "Recovery Cave",
      "count": 3
    },
    {
      "brand": "LIFE TIME PICKLEBALL",
      "count": 3
    },
    {
      "brand": "Onix",
      "count": 2
    },
    {
      "brand": "Dude Clothing",
      "count": 2
    },
    {
      "brand": "NEW YORK",
      "count": 2
    }
  ],
  "top_arcs": [
    {
      "arc": "strategic",
      "count": 272
    },
    {
      "arc": "competitive_intensity",
      "count": 82
    },
    {
      "arc": "unknown",
      "count": 39
    },
    {
      "arc": "teaching_moment",
      "count": 21
    },
    {
      "arc": "grind_rally",
      "count": 21
    },
    {
      "arc": "top_play",
      "count": 16
    },
    {
      "arc": "pure_fun",
      "count": 8
    },
    {
      "arc": "error_highlight",
      "count": 6
    },
    {
      "arc": "athletic_rally",
      "count": 4
    },
    {
      "arc": "athletic",
      "count": 4
    }
  ],
  "avg_quality": 6.12,
  "avg_viral": 3.32,
  "last_updated": "2026-04-13T00:31:33.176944"
}