{
  "error": "503 UNAVAILABLE. {'error': {'code': 503, 'message': 'This model is currently experiencing high demand. Spikes in demand are usually temporary. Please ",
  "_clip_meta": {
    "uuid": "grOa19EpoAaf",
    "url": "https://cdn.courtana.com/files/production/u/01915c59-9bb7-4683-bd53-e28bddcae12e/9c1cdc8d-ba4f-41aa-b359-bef0d23876e8.mp4",
    "group_id": "3CBIGfSknanD",
    "thumbnail": "https://cdn.courtana.com/files/production/u/faad1826-b310-4602-89d2-cc8eea8444f6/65241413-be64-447b-989a-e9b0a926c4fd.jpeg",
    "name": "Panel grOa19EpoAaf",
    "type": "panel",
    "created_at": "2026-03-22T23:55:58.646900Z",
    "participants": [
      "PickleBill",
      "Cosmo"
    ]
  }
}