[
  {
    "timestamp": "2026-04-14T16:57:42.584124",
    "f1": 0.03,
    "precision": 0.016,
    "recall": 0.2,
    "true_positives": 1,
    "false_positives": 60,
    "false_negatives": 4,
    "total_predictions": 62,
    "corpus_size": 804,
    "analysis_files": 1467,
    "clips_reviewed_by_human": 7
  },
  {
    "timestamp": "2026-04-14T17:05:50.969341",
    "f1": 0.03,
    "precision": 0.016,
    "recall": 0.2,
    "true_positives": 1,
    "false_positives": 60,
    "false_negatives": 4,
    "total_predictions": 62,
    "corpus_size": 804,
    "analysis_files": 1469,
    "clips_reviewed_by_human": 7
  },
  {
    "timestamp": "2026-04-14T17:15:14.508807",
    "f1": 0.03,
    "precision": 0.016,
    "recall": 0.2,
    "true_positives": 1,
    "false_positives": 60,
    "false_negatives": 4,
    "total_predictions": 62,
    "corpus_size": 804,
    "analysis_files": 1469,
    "clips_reviewed_by_human": 7
  },
  {
    "timestamp": "2026-04-14T18:23:33.675322",
    "f1": 0.03,
    "precision": 0.016,
    "recall": 0.2,
    "true_positives": 1,
    "false_positives": 60,
    "false_negatives": 4,
    "total_predictions": 62,
    "corpus_size": 804,
    "analysis_files": 1487,
    "clips_reviewed_by_human": 7
  },
  {
    "timestamp": "2026-04-14T18:26:46.607043",
    "f1": 0.03,
    "precision": 0.016,
    "recall": 0.2,
    "true_positives": 1,
    "false_positives": 60,
    "false_negatives": 4,
    "total_predictions": 62,
    "corpus_size": 804,
    "analysis_files": 1487,
    "clips_reviewed_by_human": 7
  },
  {
    "timestamp": "2026-04-14T18:49:04.920415",
    "f1": 0.493,
    "precision": 0.439,
    "recall": 0.562,
    "true_positives": 523,
    "false_positives": 668,
    "false_negatives": 407,
    "total_predictions": 2742,
    "corpus_size": 822,
    "analysis_files": 1507,
    "clips_reviewed_by_human": 7
  }
]